arrayish/__init__.py
arrayish/_version.py
arrayish/defaults.py
arrayish-0.0.1.dist-info/METADATA
arrayish-0.0.1.dist-info/RECORD
arrayish-0.0.1.dist-info/WHEEL
arrayish-0.0.1.dist-info/top_level.txt
