Metadata-Version: 2.1
Name: arrayish
Version: 0.0.1
Summary: A package to allow downstream inter-compatibility for Numpy-compatible array structures
Home-page: https://github.com/hameerabbasi/arrayish
Maintainer: Hameer Abbasi
Maintainer-email: hameerabbasi@yahoo.com
License: BSD
Platform: UNKNOWN
Requires-Dist: numpy
Requires-Dist: multipledispatch
